camera_z_transition/__init__.py
camera_z_transition/camera_motion.py
camera_z_transition-1.0.dist-info/LICENSE
camera_z_transition-1.0.dist-info/METADATA
camera_z_transition-1.0.dist-info/WHEEL
camera_z_transition-1.0.dist-info/top_level.txt
camera_z_transition-1.0.dist-info/RECORD
