Metadata-Version: 2.1
Name: camera-z-transition
Version: 1.0
Summary: This package provides quick and easy way to estimate the camera transition on the z axis given an optical flow.
Home-page: https://github.com/stamas02/camera_z_transition
Author: Tamas Suveges
Author-email: stamas01@gmail.com
License: MIT
Download-URL: https://github.com/stamas02/camera_z_transition/archive/v_01.tar.gz
Keywords: video,optical-flow,camera,camera-motion,motion field,camera transition,camera movement
Platform: UNKNOWN
Classifier: Development Status :: 4 - Beta
Classifier: Intended Audience :: Developers
Classifier: Topic :: Software Development :: Build Tools
Classifier: License :: OSI Approved :: MIT License
Classifier: Programming Language :: Python :: 3
Classifier: Programming Language :: Python :: 3.4
Classifier: Programming Language :: Python :: 3.5
Classifier: Programming Language :: Python :: 3.6
Classifier: Programming Language :: Python :: 3.7
Classifier: Programming Language :: Python :: 3.8
Requires-Dist: scipy
Requires-Dist: numpy
